cola/__init__.py
cola/__main__.py
cola/_version.py
cola/actions.py
cola/app.py
cola/cmd.py
cola/cmds.py
cola/compat.py
cola/core.py
cola/dag.py
cola/decorators.py
cola/diffparse.py
cola/difftool.py
cola/display.py
cola/editpatch.py
cola/fsmonitor.py
cola/git.py
cola/gitcfg.py
cola/gitcmds.py
cola/gravatar.py
cola/guicmds.py
cola/hidpi.py
cola/hotkeys.py
cola/i18n.py
cola/icons.py
cola/inotify.py
cola/interaction.py
cola/main.py
cola/polib.py
cola/qtcompat.py
cola/qtutils.py
cola/resources.py
cola/sequenceeditor.py
cola/settings.py
cola/spellcheck.py
cola/textwrap.py
cola/themes.py
cola/utils.py
cola/version.py
cola/bin/ssh-askpass
cola/bin/ssh-askpass-darwin
cola/data/hotkeys.html
cola/data/hotkeys_de.html
cola/data/hotkeys_zh_CN.html
cola/data/hotkeys_zh_TW.html
cola/i18n/README.md
cola/i18n/cs.po
cola/i18n/de.po
cola/i18n/es.po
cola/i18n/fr.po
cola/i18n/git-cola.pot
cola/i18n/hu.po
cola/i18n/id_ID.po
cola/i18n/it.po
cola/i18n/ja.po
cola/i18n/pl.po
cola/i18n/pt_BR.po
cola/i18n/ru.po
cola/i18n/sv.po
cola/i18n/ta.po
cola/i18n/tr_TR.po
cola/i18n/uk.po
cola/i18n/zh_CN.po
cola/i18n/zh_TW.po
cola/i18n/glossary/de.po
cola/i18n/glossary/it.po
cola/i18n/glossary/zh_cn.po
cola/i18n/glossary/zh_tw.po
cola/icons/README.md
cola/icons/a-z-order.svg
cola/icons/arrow-down.svg
cola/icons/arrow-up.svg
cola/icons/check.svg
cola/icons/circle-slash-red.svg
cola/icons/circle-slash.svg
cola/icons/clock-fill.svg
cola/icons/desktop-download.svg
cola/icons/diff.svg
cola/icons/document-save-symbolic.svg
cola/icons/edit-copy.svg
cola/icons/edit-cut.svg
cola/icons/edit-paste.svg
cola/icons/edit-redo.svg
cola/icons/edit-select-all.svg
cola/icons/edit-undo.svg
cola/icons/ellipsis.svg
cola/icons/eye.svg
cola/icons/file-binary.svg
cola/icons/file-code.svg
cola/icons/file-directory.svg
cola/icons/file-download.svg
cola/icons/file-media.svg
cola/icons/file-text.svg
cola/icons/file-zip.svg
cola/icons/fold.svg
cola/icons/folder-new.svg
cola/icons/folder.svg
cola/icons/gear-solid.svg
git_cola-4.17.1.dist-info/licenses/LICENSE
git_cola-4.17.1.dist-info/METADATA
git_cola-4.17.1.dist-info/WHEEL
git_cola-4.17.1.dist-info/entry_points.txt
git_cola-4.17.1.dist-info/top_level.txt
git_cola-4.17.1.dist-info/RECORD
