Metadata-Version: 2.4
Name: git-cola
Version: 4.17.1
Summary: Git Cola is a powerful Git GUI with a slick and intuitive user interface.
Author-email: David Aguilar <davvid@gmail.com>
License-Expression: GPL-2.0
Classifier: Development Status :: 6 - Mature
Classifier: Intended Audience :: Developers
Classifier: Intended Audience :: End Users/Desktop
Classifier: Programming Language :: Python :: 3
Classifier: Topic :: Software Development :: Libraries :: Python Modules
Classifier: Topic :: Software Development :: Version Control :: Git
License-File: LICENSE
Requires-Dist: importlib_metadata; python_version < "3.8"
Requires-Dist: polib>=1.0.0
Requires-Dist: qtpy>=1.1.0
Provides-Extra: testing
Requires-Dist: pytest-checkdocs>=2.4; extra == "testing"
Requires-Dist: pytest-enabler>=2.2; extra == "testing"
Requires-Dist: pytest-ruff>=0.2.1; extra == "testing"
Requires-Dist: pytest>=6; extra == "testing"
Provides-Extra: docs
Requires-Dist: furo; extra == "docs"
Requires-Dist: rst.linker>=1.9; extra == "docs"
Requires-Dist: sphinx; extra == "docs"
Provides-Extra: extras
Requires-Dist: notify2; extra == "extras"
Requires-Dist: pyobjc; sys_platform == "darwin" and extra == "extras"
Requires-Dist: send2trash; extra == "extras"
Provides-Extra: dev
Requires-Dist: cercis; extra == "dev"
Requires-Dist: pyupgrade; extra == "dev"
Provides-Extra: build
Requires-Dist: build; extra == "build"
Requires-Dist: pynsist; extra == "build"
Requires-Dist: setuptools>=64.0; extra == "build"
Requires-Dist: setuptools_scm[toml]>=3.4.1; extra == "build"
Requires-Dist: twine; extra == "build"
Requires-Dist: wheel; extra == "build"
Provides-Extra: pyqt5
Requires-Dist: PyQt5; extra == "pyqt5"
Provides-Extra: pyqt6
Requires-Dist: PyQt6; extra == "pyqt6"
Provides-Extra: pyside2
Requires-Dist: PySide2; extra == "pyside2"
Provides-Extra: pyside6
Requires-Dist: PySide6; extra == "pyside6"
Dynamic: license-file
